nmdc_api_utilities/__init__.py
nmdc_api_utilities/auth.py
nmdc_api_utilities/biosample_search.py
nmdc_api_utilities/calibration_search.py
nmdc_api_utilities/chemical_entity_search.py
nmdc_api_utilities/collecting_biosamples_from_site_search.py
nmdc_api_utilities/collection_search.py
nmdc_api_utilities/configuration_search.py
nmdc_api_utilities/data_generation_search.py
nmdc_api_utilities/data_object_search.py
nmdc_api_utilities/data_processing.py
nmdc_api_utilities/decorators.py
nmdc_api_utilities/example_usage.py
nmdc_api_utilities/field_research_site_search.py
nmdc_api_utilities/functional_annotation_agg_search.py
nmdc_api_utilities/functional_search.py
nmdc_api_utilities/instrument_search.py
nmdc_api_utilities/lat_long_filters.py
nmdc_api_utilities/manifest_search.py
nmdc_api_utilities/material_processing_search.py
nmdc_api_utilities/metadata.py
nmdc_api_utilities/minter.py
nmdc_api_utilities/nmdc_search.py
nmdc_api_utilities/processed_sample_search.py
nmdc_api_utilities/protocol_execution_search.py
nmdc_api_utilities/storage_process_search.py
nmdc_api_utilities/study_search.py
nmdc_api_utilities/utils.py
nmdc_api_utilities/visualize.py
nmdc_api_utilities/workflow_execution_search.py
nmdc_api_utilities/test/__init__.py
nmdc_api_utilities/test/test_biosample.py
nmdc_api_utilities/test/test_collection.py
nmdc_api_utilities/test/test_data_object.py
nmdc_api_utilities/test/test_func_ann_agg.py
nmdc_api_utilities/test/test_instrument.py
nmdc_api_utilities/test/test_linked_instances.py
nmdc_api_utilities/test/test_metadata.py
nmdc_api_utilities/test/test_mint.py
nmdc_api_utilities/test/test_nmdcsearch.py
nmdc_api_utilities/test/test_notebooks.py
nmdc_api_utilities/test/test_study.py
nmdc_api_utilities-0.5.0.dist-info/licenses/LICENSE
nmdc_api_utilities-0.5.0.dist-info/METADATA
nmdc_api_utilities-0.5.0.dist-info/WHEEL
nmdc_api_utilities-0.5.0.dist-info/top_level.txt
nmdc_api_utilities-0.5.0.dist-info/RECORD
