Metadata-Version: 2.4
Name: nmdc_api_utilities
Version: 0.5.0
Summary: A Python library for general research functions using NMDC APIs
Author-email: Olivia Hess <olivia.hess@pnnl.gov>
Classifier: Programming Language :: Python :: 3
Classifier: Operating System :: OS Independent
Requires-Python: >=3.10
License-File: LICENSE
Requires-Dist: pandas
Requires-Dist: requests
Requires-Dist: matplotlib
Requires-Dist: dotenv
Dynamic: license-file
